{
  "title": "Kegareboshi",
  "description": "",
  "artist": "Satou Kuuki",
  "author": "Satou Kuuki",
  "cover": "https://i.nhentai.net/galleries/2119752/1.jpg",
  "chapters": {
    "1": {
      "title": "1",
      "volume": "1",
      "last_updated": "1689967397",
      "groups": {
        "": [
          "https://i.nhentai.net/galleries/2119752/2.jpg",
          "https://i.nhentai.net/galleries/2119752/3.jpg",
          "https://i.nhentai.net/galleries/2119752/4.jpg",
          "https://i.nhentai.net/galleries/2119752/5.jpg",
          "https://i.nhentai.net/galleries/2119752/6.jpg",
          "https://i.nhentai.net/galleries/2119752/7.jpg",
          "https://i.nhentai.net/galleries/2119752/8.jpg",
          "https://i.nhentai.net/galleries/2119752/9.jpg",
          "https://i.nhentai.net/galleries/2119752/10.jpg",
          "https://i.nhentai.net/galleries/2119752/11.jpg",
          "https://i.nhentai.net/galleries/2119752/12.jpg",
          "https://i.nhentai.net/galleries/2119752/13.jpg",
          "https://i.nhentai.net/galleries/2119752/14.jpg",
          "https://i.nhentai.net/galleries/2119752/15.jpg",
          "https://i.nhentai.net/galleries/2119752/16.jpg",
          "https://i.nhentai.net/galleries/2119752/17.jpg",
          "https://i.nhentai.net/galleries/2119752/18.jpg",
          "https://i.nhentai.net/galleries/2119752/19.jpg",
          "https://i.nhentai.net/galleries/2119752/20.jpg",
          "https://i.nhentai.net/galleries/2119752/21.jpg",
          "https://i.nhentai.net/galleries/2119752/22.jpg",
          "https://i.nhentai.net/galleries/2119752/23.jpg",
          "https://i.nhentai.net/galleries/2119752/24.jpg",
          "https://i.nhentai.net/galleries/2119752/25.jpg",
          "https://i.nhentai.net/galleries/2119752/26.jpg",
          "https://i.nhentai.net/galleries/2119752/27.jpg",
          "https://i.nhentai.net/galleries/2119752/28.jpg",
          "https://i.nhentai.net/galleries/2119752/29.jpg",
          "https://i.nhentai.net/galleries/2119752/30.jpg",
          "https://i.nhentai.net/galleries/2119752/31.jpg",
          "https://i.nhentai.net/galleries/2119752/32.jpg",
          "https://i.nhentai.net/galleries/2119752/33.jpg",
          "https://i.nhentai.net/galleries/2119752/34.jpg"
        ]
      }
    },
    "2": {
      "title": "2",
      "volume": "1",
      "last_updated": "1689970031",
      "groups": {
        "": [
          "https://i.nhentai.net/galleries/2373446/1.jpg",
          "https://i.nhentai.net/galleries/2373446/2.jpg",
          "https://i.nhentai.net/galleries/2373446/3.jpg",
          "https://i.nhentai.net/galleries/2373446/4.jpg",
          "https://i.nhentai.net/galleries/2373446/5.jpg",
          "https://i.nhentai.net/galleries/2373446/6.jpg",
          "https://i.nhentai.net/galleries/2373446/7.jpg",
          "https://i.nhentai.net/galleries/2373446/8.jpg",
          "https://i.nhentai.net/galleries/2373446/9.jpg",
          "https://i.nhentai.net/galleries/2373446/10.jpg",
          "https://i.nhentai.net/galleries/2373446/11.jpg",
          "https://i.nhentai.net/galleries/2373446/12.jpg",
          "https://i.nhentai.net/galleries/2373446/13.jpg",
          "https://i.nhentai.net/galleries/2373446/14.jpg",
          "https://i.nhentai.net/galleries/2373446/15.jpg",
          "https://i.nhentai.net/galleries/2373446/16.jpg",
          "https://i.nhentai.net/galleries/2373446/17.jpg",
          "https://i.nhentai.net/galleries/2373446/18.jpg",
          "https://i.nhentai.net/galleries/2373446/19.jpg",
          "https://i.nhentai.net/galleries/2373446/20.jpg",
          "https://i.nhentai.net/galleries/2373446/21.jpg",
          "https://i.nhentai.net/galleries/2373446/22.jpg",
          "https://i.nhentai.net/galleries/2373446/23.jpg",
          "https://i.nhentai.net/galleries/2373446/24.jpg",
          "https://i.nhentai.net/galleries/2373446/25.jpg",
          "https://i.nhentai.net/galleries/2373446/26.jpg",
          "https://i.nhentai.net/galleries/2373446/27.jpg",
          "https://i.nhentai.net/galleries/2373446/28.jpg",
          "https://i.nhentai.net/galleries/2373446/29.jpg",
          "https://i.nhentai.net/galleries/2373446/30.jpg",
          "https://i.nhentai.net/galleries/2373446/31.jpg",
          "https://i.nhentai.net/galleries/2373446/32.jpg",
          "https://i.nhentai.net/galleries/2373446/33.jpg",
          "https://i.nhentai.net/galleries/2373446/34.jpg",
          "https://i.nhentai.net/galleries/2373446/35.jpg",
          "https://i.nhentai.net/galleries/2373446/36.jpg",
          "https://i.nhentai.net/galleries/2373446/37.jpg",
          "https://i.nhentai.net/galleries/2373446/38.jpg",
          "https://i.nhentai.net/galleries/2373446/39.jpg",
          "https://i.nhentai.net/galleries/2373446/40.jpg",
          "https://i.nhentai.net/galleries/2373446/41.jpg",
          "https://i.nhentai.net/galleries/2373446/42.jpg",
          "https://i.nhentai.net/galleries/2373446/43.jpg"
        ]
      }
    },
    "3": {
      "title": "3",
      "volume": "1",
      "last_updated": "1689970701",
      "groups": {
        "": [
          "https://i.nhentai.net/galleries/2430599/1.jpg",
          "https://i.nhentai.net/galleries/2430599/2.jpg",
          "https://i.nhentai.net/galleries/2430599/3.jpg",
          "https://i.nhentai.net/galleries/2430599/4.jpg",
          "https://i.nhentai.net/galleries/2430599/5.jpg",
          "https://i.nhentai.net/galleries/2430599/6.jpg",
          "https://i.nhentai.net/galleries/2430599/7.jpg",
          "https://i.nhentai.net/galleries/2430599/8.jpg",
          "https://i.nhentai.net/galleries/2430599/9.jpg",
          "https://i.nhentai.net/galleries/2430599/10.jpg",
          "https://i.nhentai.net/galleries/2430599/11.jpg",
          "https://i.nhentai.net/galleries/2430599/12.jpg",
          "https://i.nhentai.net/galleries/2430599/13.jpg",
          "https://i.nhentai.net/galleries/2430599/14.jpg",
          "https://i.nhentai.net/galleries/2430599/15.jpg",
          "https://i.nhentai.net/galleries/2430599/16.jpg",
          "https://i.nhentai.net/galleries/2430599/17.jpg",
          "https://i.nhentai.net/galleries/2430599/18.jpg",
          "https://i.nhentai.net/galleries/2430599/19.jpg",
          "https://i.nhentai.net/galleries/2430599/20.jpg",
          "https://i.nhentai.net/galleries/2430599/21.jpg",
          "https://i.nhentai.net/galleries/2430599/22.jpg",
          "https://i.nhentai.net/galleries/2430599/23.jpg",
          "https://i.nhentai.net/galleries/2430599/24.jpg",
          "https://i.nhentai.net/galleries/2430599/25.jpg",
          "https://i.nhentai.net/galleries/2430599/26.jpg",
          "https://i.nhentai.net/galleries/2430599/27.jpg",
          "https://i.nhentai.net/galleries/2430599/28.jpg",
          "https://i.nhentai.net/galleries/2430599/29.jpg",
          "https://i.nhentai.net/galleries/2430599/30.jpg"
        ]
      }
    }
  }
}